mkdocs_exclude/__init__.py
mkdocs_exclude/plugin.py
mkdocs_exclude-1.0.0.dist-info/DESCRIPTION.rst
mkdocs_exclude-1.0.0.dist-info/METADATA
mkdocs_exclude-1.0.0.dist-info/RECORD
mkdocs_exclude-1.0.0.dist-info/WHEEL
mkdocs_exclude-1.0.0.dist-info/entry_points.txt
mkdocs_exclude-1.0.0.dist-info/metadata.json
mkdocs_exclude-1.0.0.dist-info/top_level.txt
