Metadata-Version: 2.0
Name: mkdocs-exclude
Version: 1.0.0
Summary: A mkdocs plugin that lets you exclude files or trees.
Home-page: https://github.com/apenwarr/mkdocs-exclude
Author: Avery Pennarun
Author-email: apenwarr@gmail.com
License: Apache
Platform: UNKNOWN
Requires-Dist: mkdocs
